CHANGELOG.md
datev_splitter/__init__.py
datev_splitter/__version__.py
datev_splitter/pdf_extract.py
Datev_Splitter-0.5.0.dist-info/entry_points.txt
Datev_Splitter-0.5.0.dist-info/WHEEL
Datev_Splitter-0.5.0.dist-info/METADATA
Datev_Splitter-0.5.0.dist-info/RECORD
